PanjSim/Countrys.py
PanjSim/__init__.py
PanjSim/client.py
PanjSim/errors.py
PanjSim/http_client.py
PanjSim/products/__init__.py
PanjSim/products/products.py
PanjSim/purchase/__init__.py
PanjSim/purchase/management.py
PanjSim/purchase/purchase.py
PanjSim/types/__init__.py
PanjSim/types/_operators.py
PanjSim/types/_order.py
PanjSim/types/_products.py
PanjSim/user/__init__.py
PanjSim/user/user.py
PanjSim/vendor/__init__.py
PanjSim/vendor/vendor.py
PanjSim-1.0.4.dist-info/LICENSE
PanjSim-1.0.4.dist-info/METADATA
PanjSim-1.0.4.dist-info/WHEEL
PanjSim-1.0.4.dist-info/top_level.txt
PanjSim-1.0.4.dist-info/RECORD
