Metadata-Version: 2.1
Name: PanjSim
Version: 1.0.4
Summary: A simple Python API for 5sim.net
Home-page: https://github.com/abbas-bachari/PanjSim
Author: Abbas Bachari
Author-email: abbas-bachari@hotmail.com
License: MIT
Project-URL: Homepage, https://github.com/abbas-bachari/PanjSim
Project-URL: Documentation, https://github.com/abbas-bachari/PanjSim
Project-URL: Source, https://github.com/abbas-bachari/PanjSim/
Project-URL: Tracker, https://github.com/abbas-bachari/PanjSim/issues
Keywords: 5sim,5sim-sdk,5sim-pythom,PanjSim,virtual numbers,api,5sim-api,abbas bachari
Classifier: Intended Audience :: Developers
Classifier: Topic :: Software Development :: Libraries :: Python Modules
Classifier: License :: OSI Approved :: MIT License
Classifier: Operating System :: OS Independent
Classifier: Programming Language :: Python
Classifier: Programming Language :: Python :: 3.7
Classifier: Programming Language :: Python :: 3.9
Classifier: Programming Language :: Python :: 3.10
Classifier: Programming Language :: Python :: 3.11
Requires-Python: >=3.7
License-File: LICENSE
Requires-Dist: requests
